httperrors/__init__.py
httperrors/errors.py
httperrors-1.0.0.dist-info/DESCRIPTION.rst
httperrors-1.0.0.dist-info/METADATA
httperrors-1.0.0.dist-info/RECORD
httperrors-1.0.0.dist-info/WHEEL
httperrors-1.0.0.dist-info/metadata.json
httperrors-1.0.0.dist-info/top_level.txt
