Metadata-Version: 2.1
Name: httperrors
Version: 1.0.0
Summary: Library that provides a easy to use set of http errors along with useful descriptions
Home-page: https://github.com/LautaroNavarro/httperrors
Author: Lautaro Navarro
Author-email: navarro_lautaro@hotmail.com
License: UNKNOWN
Platform: UNKNOWN
Classifier: Development Status :: 3 - Alpha
Classifier: Intended Audience :: Developers
Classifier: Topic :: Software Development :: Build Tools
Classifier: License :: OSI Approved :: GNU Affero General Public License v3
Classifier: Programming Language :: Python :: 3
Classifier: Programming Language :: Python :: 3.4
Classifier: Programming Language :: Python :: 3.5
Classifier: Programming Language :: Python :: 3.6
Requires-Python: >=3.0
